{
  "weights": {
    "prime": 0.20851528384279475,
    "class": 0.16703056768558952,
    "spd3": 0.15283842794759825,
    "pc3": 0.1943231441048035,
    "jt": 0.13864628820960698,
    "ml": 0.13864628820960698
  },
  "tier_thresholds": {
    "SNIPER": "composite>=90 AND prime#1 AND pc3<=2",
    "EDGE": "composite>=80 AND prime<=2",
    "DUAL": "composite>=70 AND prime<=3",
    "RECON": "composite>=60 OR (prime<=3 AND 2+ top-3 confirms)",
    "PASS": "below all"
  },
  "tier_hit_rates": {
    "EDGE": {
      "n": 12,
      "anchor_win_rate": 0.25,
      "winner_top3_rate": 0.6666666666666666
    },
    "DUAL": {
      "n": 6,
      "anchor_win_rate": 0.16666666666666666,
      "winner_top3_rate": 0.5
    },
    "SNIPER": {
      "n": 2,
      "anchor_win_rate": 0.5,
      "winner_top3_rate": 0.5
    },
    "RECON": {
      "n": 3,
      "anchor_win_rate": 0.0,
      "winner_top3_rate": 0.3333333333333333
    }
  },
  "overall_anchor_win_rate": 0.21739130434782608,
  "n_races": 23,
  "race_grades": [
    {
      "track": "belmont",
      "date": "2026-06-11",
      "race": 1,
      "winner_pp": "1",
      "anchor_pp": "7",
      "tier": "EDGE",
      "composite": 95.7,
      "anchor_won": false,
      "winner_rank_in_composite": 8,
      "recommendation": "Strong anchor. $15 WIN + $10 EXA key over top-3.",
      "confirms": 6
    },
    {
      "track": "belmont",
      "date": "2026-06-11",
      "race": 2,
      "winner_pp": "2",
      "anchor_pp": "2",
      "tier": "EDGE",
      "composite": 88.0,
      "anchor_won": true,
      "winner_rank_in_composite": 1,
      "recommendation": "Strong anchor. $15 WIN + $10 EXA key over top-3.",
      "confirms": 5
    },
    {
      "track": "belmont",
      "date": "2026-06-11",
      "race": 3,
      "winner_pp": "7",
      "anchor_pp": "4",
      "tier": "EDGE",
      "composite": 85.9,
      "anchor_won": false,
      "winner_rank_in_composite": 2,
      "recommendation": "Strong anchor. $15 WIN + $10 EXA key over top-3.",
      "confirms": 5
    },
    {
      "track": "belmont",
      "date": "2026-06-11",
      "race": 4,
      "winner_pp": "1",
      "anchor_pp": "4",
      "tier": "DUAL",
      "composite": 84.9,
      "anchor_won": false,
      "winner_rank_in_composite": 4,
      "recommendation": "Two-horse play. $10 EXA box anchor with 2nd-best by composite. NO WIN.",
      "confirms": 5
    },
    {
      "track": "belmont",
      "date": "2026-06-11",
      "race": 5,
      "winner_pp": "11",
      "anchor_pp": "11",
      "tier": "EDGE",
      "composite": 88.2,
      "anchor_won": true,
      "winner_rank_in_composite": 1,
      "recommendation": "Strong anchor. $15 WIN + $10 EXA key over top-3.",
      "confirms": 4
    },
    {
      "track": "belmont",
      "date": "2026-06-11",
      "race": 6,
      "winner_pp": "3",
      "anchor_pp": "3",
      "tier": "EDGE",
      "composite": 87.5,
      "anchor_won": true,
      "winner_rank_in_composite": 1,
      "recommendation": "Strong anchor. $15 WIN + $10 EXA key over top-3.",
      "confirms": 5
    },
    {
      "track": "belmont",
      "date": "2026-06-11",
      "race": 7,
      "winner_pp": "3",
      "anchor_pp": "2",
      "tier": "EDGE",
      "composite": 85.4,
      "anchor_won": false,
      "winner_rank_in_composite": 2,
      "recommendation": "Strong anchor. $15 WIN + $10 EXA key over top-3.",
      "confirms": 4
    },
    {
      "track": "belmont",
      "date": "2026-06-11",
      "race": 8,
      "winner_pp": "12",
      "anchor_pp": "5",
      "tier": "DUAL",
      "composite": 81.6,
      "anchor_won": false,
      "winner_rank_in_composite": 8,
      "recommendation": "Two-horse play. $10 EXA box anchor with 2nd-best by composite. NO WIN.",
      "confirms": 4
    },
    {
      "track": "churchill",
      "date": "2026-06-11",
      "race": 1,
      "winner_pp": "3",
      "anchor_pp": "5",
      "tier": "EDGE",
      "composite": 84.7,
      "anchor_won": false,
      "winner_rank_in_composite": 2,
      "recommendation": "Strong anchor. $15 WIN + $10 EXA key over top-3.",
      "confirms": 5
    },
    {
      "track": "churchill",
      "date": "2026-06-11",
      "race": 2,
      "winner_pp": "7",
      "anchor_pp": "4",
      "tier": "EDGE",
      "composite": 86.1,
      "anchor_won": false,
      "winner_rank_in_composite": 5,
      "recommendation": "Strong anchor. $15 WIN + $10 EXA key over top-3.",
      "confirms": 6
    },
    {
      "track": "churchill",
      "date": "2026-06-11",
      "race": 3,
      "winner_pp": "2",
      "anchor_pp": "2",
      "tier": "SNIPER",
      "composite": 97.2,
      "anchor_won": true,
      "winner_rank_in_composite": 1,
      "recommendation": "Lock anchor. Max ticket: $25 WIN + $20 EXA key over top-3 by composite.",
      "confirms": 6
    },
    {
      "track": "churchill",
      "date": "2026-06-11",
      "race": 4,
      "winner_pp": "4",
      "anchor_pp": "8",
      "tier": "RECON",
      "composite": 53.2,
      "anchor_won": false,
      "winner_rank_in_composite": 9,
      "recommendation": "RECON STAMP \u2014 lower conviction. $2-5 EXA box only. Watch live odds.",
      "confirms": 2
    },
    {
      "track": "churchill",
      "date": "2026-06-11",
      "race": 5,
      "winner_pp": "7",
      "anchor_pp": "8",
      "tier": "RECON",
      "composite": 75.3,
      "anchor_won": false,
      "winner_rank_in_composite": 2,
      "recommendation": "RECON STAMP \u2014 lower conviction. $2-5 EXA box only. Watch live odds.",
      "confirms": 4
    },
    {
      "track": "churchill",
      "date": "2026-06-11",
      "race": 6,
      "winner_pp": "1",
      "anchor_pp": "3",
      "tier": "EDGE",
      "composite": 83.2,
      "anchor_won": false,
      "winner_rank_in_composite": 2,
      "recommendation": "Strong anchor. $15 WIN + $10 EXA key over top-3.",
      "confirms": 5
    },
    {
      "track": "churchill",
      "date": "2026-06-11",
      "race": 7,
      "winner_pp": "1",
      "anchor_pp": "3",
      "tier": "DUAL",
      "composite": 79.4,
      "anchor_won": false,
      "winner_rank_in_composite": 2,
      "recommendation": "Two-horse play. $10 EXA box anchor with 2nd-best by composite. NO WIN.",
      "confirms": 5
    },
    {
      "track": "churchill",
      "date": "2026-06-11",
      "race": 8,
      "winner_pp": "9",
      "anchor_pp": "2",
      "tier": "EDGE",
      "composite": 96.6,
      "anchor_won": false,
      "winner_rank_in_composite": 9,
      "recommendation": "Strong anchor. $15 WIN + $10 EXA key over top-3.",
      "confirms": 6
    },
    {
      "track": "belmont",
      "date": "2026-06-12",
      "race": 1,
      "winner_pp": "6",
      "anchor_pp": "2",
      "tier": "DUAL",
      "composite": 77.8,
      "anchor_won": false,
      "winner_rank_in_composite": 5,
      "recommendation": "Two-horse play. $10 EXA box anchor with 2nd-best by composite. NO WIN.",
      "confirms": 4
    },
    {
      "track": "belmont",
      "date": "2026-06-12",
      "race": 2,
      "winner_pp": "1",
      "anchor_pp": "4",
      "tier": "EDGE",
      "composite": 88.5,
      "anchor_won": false,
      "winner_rank_in_composite": 3,
      "recommendation": "Strong anchor. $15 WIN + $10 EXA key over top-3.",
      "confirms": 5
    },
    {
      "track": "belmont",
      "date": "2026-06-12",
      "race": 3,
      "winner_pp": "6",
      "anchor_pp": "3",
      "tier": "SNIPER",
      "composite": 90.8,
      "anchor_won": false,
      "winner_rank_in_composite": 4,
      "recommendation": "Lock anchor. Max ticket: $25 WIN + $20 EXA key over top-3 by composite.",
      "confirms": 6
    },
    {
      "track": "belmont",
      "date": "2026-06-12",
      "race": 4,
      "winner_pp": "6",
      "anchor_pp": "4",
      "tier": "EDGE",
      "composite": 87.3,
      "anchor_won": false,
      "winner_rank_in_composite": 6,
      "recommendation": "Strong anchor. $15 WIN + $10 EXA key over top-3.",
      "confirms": 5
    },
    {
      "track": "belmont",
      "date": "2026-06-12",
      "race": 5,
      "winner_pp": "1",
      "anchor_pp": "1",
      "tier": "DUAL",
      "composite": 78.6,
      "anchor_won": true,
      "winner_rank_in_composite": 1,
      "recommendation": "Two-horse play. $10 EXA box anchor with 2nd-best by composite. NO WIN.",
      "confirms": 5
    },
    {
      "track": "belmont",
      "date": "2026-06-12",
      "race": 6,
      "winner_pp": "6",
      "anchor_pp": "1",
      "tier": "RECON",
      "composite": 50.4,
      "anchor_won": false,
      "winner_rank_in_composite": 5,
      "recommendation": "RECON STAMP \u2014 lower conviction. $2-5 EXA box only. Watch live odds.",
      "confirms": 3
    },
    {
      "track": "belmont",
      "date": "2026-06-12",
      "race": 7,
      "winner_pp": "6",
      "anchor_pp": "4",
      "tier": "DUAL",
      "composite": 75.3,
      "anchor_won": false,
      "winner_rank_in_composite": 3,
      "recommendation": "Two-horse play. $10 EXA box anchor with 2nd-best by composite. NO WIN.",
      "confirms": 3
    }
  ]
}